whenever/__init__.py
whenever/__init__.pyi
whenever/_core.py
whenever/_pywhenever.py
whenever/_utils.py
whenever/py.typed
whenever/_tz/__init__.py
whenever/_tz/common.py
whenever/_tz/posix.py
whenever/_tz/system.py
whenever/_tz/tzif.py
whenever-0.9.4.dist-info/licenses/LICENSE
whenever-0.9.4.dist-info/METADATA
whenever-0.9.4.dist-info/WHEEL
whenever-0.9.4.dist-info/top_level.txt
whenever-0.9.4.dist-info/RECORD
