Metadata-Version: 2.4
Name: whenever
Version: 0.9.4
Classifier: Development Status :: 4 - Beta
Classifier: Intended Audience :: Developers
Classifier: Operating System :: MacOS
Classifier: Operating System :: Microsoft :: Windows
Classifier: Operating System :: POSIX :: Linux
Classifier: Programming Language :: Python :: 3
Classifier: Programming Language :: Python :: 3.9
Classifier: Programming Language :: Python :: 3.10
Classifier: Programming Language :: Python :: 3.11
Classifier: Programming Language :: Python :: 3.12
Classifier: Programming Language :: Python :: 3.13
Classifier: Programming Language :: Python :: 3.14
Classifier: Programming Language :: Python :: Implementation :: CPython
Classifier: Programming Language :: Python :: Implementation :: PyPy
Classifier: Programming Language :: Python :: Free Threading :: 2 - Beta
Classifier: Programming Language :: Python
Classifier: Programming Language :: Rust
Classifier: Typing :: Typed
Requires-Dist: tzdata>=2020.1 ; sys_platform == 'win32'
Requires-Dist: tzlocal>=4.0 ; sys_platform != 'darwin' and sys_platform != 'linux'
License-File: LICENSE
License-File: LICENSE-THIRD-PARTY
Summary: Modern datetime library for Python
Keywords: datetime,typesafe,rust,date,time,timezone,utc,zoneinfo,tzdata,tzdb
Author-email: Arie Bovenberg <a.c.bovenberg@gmail.com>
Maintainer-email: Arie Bovenberg <a.c.bovenberg@gmail.com>
License-Expression: MIT
Requires-Python: >=3.9
Project-URL: Documentation, https://whenever.readthedocs.io
Project-URL: Repository, https://github.com/ariebovenberg/whenever
Project-URL: Issues, https://github.com/ariebovenberg/whenever/issues
Project-URL: Changelog, https://github.com/ariebovenberg/whenever/blob/main/CHANGELOG.md
